proman/cli.py
proman/config.py
proman/environment.py
proman/manager.py
proman/paths.py
proman/processes.py
proman/server.py
proman/frontend/buttons.css
proman/frontend/chota.min.css
proman/frontend/index.html
proman/frontend/logo.svg
py_proman-0.0.1.dist-info/licenses/LICENSE
py_proman-0.0.1.dist-info/METADATA
py_proman-0.0.1.dist-info/WHEEL
py_proman-0.0.1.dist-info/entry_points.txt
py_proman-0.0.1.dist-info/top_level.txt
py_proman-0.0.1.dist-info/RECORD
